analogy_dataset/__init__.py
analogy_dataset/loader.py
analogy_dataset/data/hats_dataset.csv
hats_analogy_dataset-1.0.0.dist-info/licenses/LICENSE
hats_analogy_dataset-1.0.0.dist-info/METADATA
hats_analogy_dataset-1.0.0.dist-info/WHEEL
hats_analogy_dataset-1.0.0.dist-info/top_level.txt
hats_analogy_dataset-1.0.0.dist-info/RECORD
