Metadata-Version: 2.4
Name: hats-analogy-dataset
Version: 1.0.0
Summary: HATS: Hindi Analogy Test Set - A controlled access package for evaluating reasoning in Large Language Models
Home-page: https://github.com/Inequilazitive/HATS-Hindi_Analogy_Test_Set
Author: Ashray Gupta, Rohan Joseph, Sunny Rai
Author-email: rohan18545@mechyd.ac.in
Project-URL: Bug Reports, https://github.com/Inequilazitive/HATS-Hindi_Analogy_Test_Set/issues
Project-URL: Source, https://github.com/Inequilazitive/HATS-Hindi_Analogy_Test_Set
Project-URL: Documentation, https://github.com/Inequilazitive/HATS-Hindi_Analogy_Test_Set/blob/main/README.md
Project-URL: Research Paper, https://aclanthology.org/
Keywords: analogy,dataset,hindi,nlp,machine learning,llm evaluation,reasoning,controlled access,test set,research
Classifier: Development Status :: 4 - Beta
Classifier: Intended Audience :: Developers
Classifier: Intended Audience :: Science/Research
Classifier: License :: OSI Approved :: MIT License
Classifier: Operating System :: OS Independent
Classifier: Programming Language :: Python :: 3
Classifier: Programming Language :: Python :: 3.7
Classifier: Programming Language :: Python :: 3.8
Classifier: Programming Language :: Python :: 3.9
Classifier: Programming Language :: Python :: 3.10
Classifier: Programming Language :: Python :: 3.11
Classifier: Programming Language :: Python :: 3.12
Classifier: Topic :: Scientific/Engineering
Classifier: Topic :: Scientific/Engineering :: Artificial Intelligence
Classifier: Topic :: Software Development :: Libraries :: Python Modules
Classifier: Topic :: Text Processing :: Linguistic
Requires-Python: >=3.7
License-File: LICENSE
Requires-Dist: pandas>=1.0.0
Requires-Dist: numpy>=1.18.0
Dynamic: author
Dynamic: author-email
Dynamic: classifier
Dynamic: description
Dynamic: description-content-type
Dynamic: home-page
Dynamic: keywords
Dynamic: license-file
Dynamic: project-url
Dynamic: requires-dist
Dynamic: requires-python
Dynamic: summary
